editfile/__init__.py
editfile/util.py
GitEdit-0.0.5.dist-info/LICENSE
GitEdit-0.0.5.dist-info/METADATA
GitEdit-0.0.5.dist-info/WHEEL
GitEdit-0.0.5.dist-info/top_level.txt
GitEdit-0.0.5.dist-info/RECORD
