Metadata-Version: 2.1
Name: GitEdit
Version: 0.0.5
Summary: Editing feature for github, markdown file.
Home-page: https://github.com/pypa/sampleproject
Author: Gobal Krishnan V
Author-email: dr.bot.engineer@gmail.com
License: UNKNOWN
Project-URL: Bug Tracker, https://github.com/pypa/sampleproject/issues
Platform: UNKNOWN
Classifier: Programming Language :: Python :: 3
Classifier: License :: OSI Approved :: MIT License
Classifier: Operating System :: OS Independent
Requires-Python: >=3.6
License-File: LICENSE
